koffi/__init__.py
koffi/_version.py
koffi/koffi.py
koffi/script.py
koffi_tools/__init__.py
koffi_tools/image_metadata.py
koffi_tools/potential_source.py
koffi-0.1.2.dist-info/LICENSE
koffi-0.1.2.dist-info/METADATA
koffi-0.1.2.dist-info/WHEEL
koffi-0.1.2.dist-info/top_level.txt
koffi-0.1.2.dist-info/RECORD
