Metadata-Version: 2.1
Name: koffi
Version: 0.1.2
Author-email: Maxine West <maxwest@uw.edu>
License: BSD 3-Clause License
Project-URL: Source Code, https://github.com/lincc-frameworks/koffi
Classifier: Development Status :: 4 - Beta
Classifier: License :: OSI Approved :: BSD License
Classifier: Intended Audience :: Developers
Classifier: Intended Audience :: Science/Research
Classifier: Operating System :: OS Independent
Classifier: Programming Language :: Python
Requires-Python: >=3.9
License-File: LICENSE
Requires-Dist: ipykernel
Requires-Dist: astropy
Requires-Dist: astroquery
Requires-Dist: tqdm
Provides-Extra: dev
Requires-Dist: black ; extra == 'dev'
Requires-Dist: jupyter ; extra == 'dev'
Requires-Dist: pre-commit ; extra == 'dev'
Requires-Dist: pytest ; extra == 'dev'
Requires-Dist: pytest-cov ; extra == 'dev'
